fastcopilot/__init__.py
fastcopilot/copilot.py
fastcopilot/exceptions.py
fastcopilot/schemas.py
fastcopilot-0.5.3.dist-info/LICENSE
fastcopilot-0.5.3.dist-info/METADATA
fastcopilot-0.5.3.dist-info/WHEEL
fastcopilot-0.5.3.dist-info/RECORD
